[
  {
    "fields": [
      {
        "validation": [
          {
            "rules": [
              {
                "flag": "presence",
                "constraint": "required"
              }
            ],
            "level": "error"
          }
        ],
        "description": "Main heading (e.g., 'POOJA')",
        "name": "title",
        "type": "string"
      },
      {
        "description": "Subheading text (e.g., 'HennArt & Makeover')",
        "name": "subtitle",
        "type": "string"
      },
      {
        "options": {
          "hotspot": true
        },
        "description": "Full-screen hero background image",
        "fields": [
          {
            "description": "Important for accessibility",
            "name": "alt",
            "type": "string",
            "title": "Alternative Text"
          }
        ],
        "name": "backgroundImage",
        "type": "image"
      },
      {
        "initialValue": true,
        "description": "Display scroll down indicator",
        "name": "showScrollCue",
        "type": "boolean",
        "title": "Show Scroll Indicator"
      }
    ],
    "name": "hero",
    "type": "document",
    "title": "Hero Section"
  },
  {
    "fields": [
      {
        "description": "Title for this media item",
        "name": "title",
        "type": "string"
      },
      {
        "options": {
          "hotspot": true
        },
        "validation": [
          {
            "rules": [
              {
                "flag": "presence",
                "constraint": "required"
              }
            ],
            "level": "error"
          }
        ],
        "description": "Main image",
        "fields": [
          {
            "description": "Important for accessibility",
            "name": "alt",
            "type": "string",
            "title": "Alternative Text"
          }
        ],
        "name": "image",
        "type": "image"
      },
      {
        "options": {
          "hotspot": true
        },
        "description": "Optional thumbnail (uses main image if not provided)",
        "name": "thumbnail",
        "type": "image",
        "title": "Thumbnail Image"
      },
      {
        "validation": [
          {
            "rules": [
              {
                "flag": "min",
                "constraint": 1
              }
            ],
            "level": "error",
            "message": "Select at least one category"
          }
        ],
        "description": "Select categories for this media item",
        "of": [
          {
            "to": [
              {
                "type": "category"
              }
            ],
            "type": "reference",
            "title": "Reference to category"
          }
        ],
        "name": "categories",
        "type": "array"
      },
      {
        "description": "Caption or description for the image",
        "name": "caption",
        "type": "text"
      },
      {
        "initialValue": false,
        "description": "Show in featured looks section",
        "name": "isFeatured",
        "type": "boolean",
        "title": "Featured"
      },
      {
        "options": {
          "list": [
            {
              "title": "Instagram",
              "value": "instagram"
            },
            {
              "title": "Other",
              "value": "other"
            }
          ]
        },
        "initialValue": "instagram",
        "name": "platform",
        "type": "string"
      },
      {
        "initialValue": 0,
        "description": "Lower numbers appear first (optional)",
        "name": "order",
        "type": "number",
        "title": "Display Order"
      }
    ],
    "name": "mediaItem",
    "type": "document"
  },
  {
    "fields": [
      {
        "validation": [
          {
            "rules": [
              {
                "flag": "presence",
                "constraint": "required"
              }
            ],
            "level": "error"
          }
        ],
        "description": "Title for this video",
        "name": "title",
        "type": "string"
      },
      {
        "options": {
          "hotspot": true
        },
        "validation": [
          {
            "rules": [
              {
                "flag": "presence",
                "constraint": "required"
              }
            ],
            "level": "error"
          }
        ],
        "description": "Video thumbnail",
        "fields": [
          {
            "name": "alt",
            "type": "string",
            "title": "Alternative Text"
          }
        ],
        "name": "thumbnail",
        "type": "image",
        "title": "Thumbnail Image"
      },
      {
        "options": {
          "list": [
            {
              "title": "Instagram Reels",
              "value": "instagram"
            },
            {
              "title": "YouTube",
              "value": "youtube"
            }
          ]
        },
        "validation": [
          {
            "rules": [
              {
                "flag": "valid",
                "constraint": [
                  "instagram",
                  "youtube"
                ]
              },
              {
                "flag": "presence",
                "constraint": "required"
              }
            ],
            "level": "error"
          }
        ],
        "name": "platform",
        "type": "string"
      },
      {
        "validation": [
          {
            "rules": [
              {
                "flag": "presence",
                "constraint": "required"
              },
              {
                "flag": "uri",
                "constraint": {
                  "options": {
                    "scheme": [
                      "/^http$/",
                      "/^https$/"
                    ],
                    "allowRelative": false,
                    "relativeOnly": false,
                    "allowCredentials": false
                  }
                }
              }
            ],
            "level": "error"
          }
        ],
        "description": "Full URL to the video (Instagram Reel or YouTube)",
        "name": "url",
        "type": "url",
        "title": "Video URL"
      },
      {
        "description": "For YouTube: video ID only (e.g., 'dQw4w9WgXcQ'). For Instagram: leave empty",
        "name": "videoId",
        "type": "string",
        "title": "Video ID"
      },
      {
        "description": "Video description or caption",
        "name": "caption",
        "type": "text"
      },
      {
        "of": [
          {
            "to": [
              {
                "type": "category"
              }
            ],
            "type": "reference",
            "title": "Reference to category"
          }
        ],
        "name": "categories",
        "type": "array"
      },
      {
        "initialValue": 0,
        "description": "Lower numbers appear first",
        "name": "order",
        "type": "number",
        "title": "Display Order"
      }
    ],
    "name": "videoItem",
    "type": "document"
  },
  {
    "fields": [
      {
        "validation": [
          {
            "rules": [
              {
                "flag": "presence",
                "constraint": "required"
              }
            ],
            "level": "error"
          }
        ],
        "description": "Full name to display",
        "name": "name",
        "type": "string"
      },
      {
        "options": {
          "hotspot": true
        },
        "description": "Profile or about image",
        "fields": [
          {
            "name": "alt",
            "type": "string",
            "title": "Alternative Text"
          }
        ],
        "name": "image",
        "type": "image"
      },
      {
        "validation": [
          {
            "rules": [
              {
                "flag": "presence",
                "constraint": "required"
              },
              {
                "flag": "max",
                "constraint": 500
              }
            ],
            "level": "error"
          }
        ],
        "description": "Short bio (2-3 lines recommended)",
        "name": "bio",
        "type": "text"
      },
      {
        "options": {
          "layout": "tags"
        },
        "description": "List of expertise areas (e.g., 'Bridal Makeup', 'Mehendi Art')",
        "of": [
          {
            "type": "string"
          }
        ],
        "name": "expertise",
        "type": "array",
        "title": "Expertise Areas"
      }
    ],
    "name": "about",
    "type": "document",
    "title": "About Section"
  },
  {
    "fields": [
      {
        "validation": [
          {
            "rules": [
              {
                "flag": "presence",
                "constraint": "required"
              }
            ],
            "level": "error"
          }
        ],
        "description": "Phone number with country code (e.g., +919876543210)",
        "name": "whatsappNumber",
        "type": "string",
        "title": "WhatsApp Number"
      },
      {
        "description": "Phone number for calls (optional)",
        "name": "phoneNumber",
        "type": "string"
      },
      {
        "description": "Instagram username without @ (e.g., 'poojahennart')",
        "name": "instagramHandle",
        "type": "string"
      },
      {
        "description": "Contact email address",
        "name": "email",
        "type": "email",
        "title": "Email Address"
      },
      {
        "initialValue": false,
        "description": "Display booking form in contact section",
        "name": "showBookingForm",
        "type": "boolean"
      }
    ],
    "name": "contact",
    "type": "document",
    "title": "Contact Information"
  },
  {
    "fields": [
      {
        "validation": [
          {
            "rules": [
              {
                "flag": "presence",
                "constraint": "required"
              },
              {
                "flag": "stringCasing",
                "constraint": "lowercase"
              },
              {
                "flag": "regex",
                "constraint": {
                  "pattern": "/^[a-z0-9-]+$/",
                  "name": "category-id",
                  "invert": false
                }
              }
            ],
            "level": "error",
            "message": "Must be lowercase letters, numbers, and hyphens only"
          }
        ],
        "description": "Unique identifier (e.g., 'bridal', 'mehendi') - lowercase, no spaces",
        "name": "id",
        "type": "string",
        "title": "Category ID"
      },
      {
        "validation": [
          {
            "rules": [
              {
                "flag": "presence",
                "constraint": "required"
              }
            ],
            "level": "error"
          }
        ],
        "description": "Display name (e.g., 'Bridal', 'Mehendi')",
        "name": "label",
        "type": "string"
      },
      {
        "initialValue": 0,
        "description": "Lower numbers appear first",
        "name": "order",
        "type": "number",
        "title": "Display Order"
      }
    ],
    "name": "category",
    "type": "document"
  }
]